plexutils/__init__.py
plexutils/__main__.py
plexutils/api/__init__.py
plexutils/api/tvdb_api.py
plexutils/config/__init__.py
plexutils/config/config.py
plexutils/config/plex_library_infos.py
plexutils/config/tvdb_credentials.py
plexutils/console/__init__.py
plexutils/console/menu.py
plexutils/console/settings_menu.py
plexutils/crawler/__init__.py
plexutils/crawler/plex_movie_crawler.py
plexutils/crawler/plex_tvshow_crawler.py
plexutils/media/__init__.py
plexutils/media/movie.py
plexutils/media/movie_list.py
plexutils/media/tvshow.py
plexutils/media/tvshow_episode.py
plexutils/media/tvshow_list.py
plexutils/media/tvshow_season.py
plexutils/shared/__init__.py
plexutils/shared/config_tools.py
plexutils/shared/date_tools.py
plexutils/shared/media_tools.py
plexutils/shared/menu_tools.py
plexutils/utils/__init__.py
plexutils/utils/movie_file_utils.py
plexutils/utils/plex_utils.py
plexutils/utils/tvdb_utils.py
plexutils/utils/tvshow_file_utils.py
plexutils-1.1.0.dist-info/AUTHORS.md
plexutils-1.1.0.dist-info/LICENSE.md
plexutils-1.1.0.dist-info/METADATA
plexutils-1.1.0.dist-info/WHEEL
plexutils-1.1.0.dist-info/entry_points.txt
plexutils-1.1.0.dist-info/RECORD
