Metadata-Version: 2.1
Name: plexutils
Version: 1.1.0
Summary: tools for plex admins
License: GPL-3.0
Author: Felix Rizzolli
Author-email: felix.rizzolli@outlook.de
Maintainer: Felix Rizzolli
Maintainer-email: felix.rizzolli@outlook.de
Requires-Python: >=3.9,<4.0
Classifier: License :: OSI Approved :: GNU General Public License v3 (GPLv3)
Classifier: Operating System :: OS Independent
Classifier: Programming Language :: Python :: 3
Classifier: Programming Language :: Python :: 3.9
Classifier: Programming Language :: Python :: 3.10
Classifier: Programming Language :: Python :: 3.11
Classifier: Programming Language :: Python :: 3.12
Classifier: Topic :: Utilities
Requires-Dist: furo (>=2024.5.6,<2025.0.0)
Requires-Dist: pyyaml (>=6.0.1,<7.0.0)
Requires-Dist: tvdb-v4-official (>=1.1.0,<2.0.0)
